bluff/__init__.py
bluff/chinese/__init__.py
bluff/holdem/__init__.py
bluff/holdem/equity.py
bluff/holdem/data/equity_model.pkl
bluff/holdem/data/sk_hand_rankings.csv
bluff-1.0.2.dist-info/LICENSE
bluff-1.0.2.dist-info/METADATA
bluff-1.0.2.dist-info/WHEEL
bluff-1.0.2.dist-info/top_level.txt
bluff-1.0.2.dist-info/RECORD
