Metadata-Version: 2.1
Name: bluff
Version: 1.0.2
Summary: Bluff is a pythonic poker framework
Home-page: https://github.com/matheusccouto/bluff
Author: Matheus Couto
Author-email: matheusccouto@gmail.com
License: UNKNOWN
Keywords: poker
Platform: UNKNOWN
Requires-Python: >=3.6
Requires-Dist: numpy (~=1.18.5)
Requires-Dist: pandas (~=1.0.4)
Requires-Dist: more-itertools (~=8.3.0)
